MANIFEST.in
README.rst
setup.py
collective/__init__.py
collective.dexteritytextindexer.egg-info/PKG-INFO
collective.dexteritytextindexer.egg-info/SOURCES.txt
collective.dexteritytextindexer.egg-info/dependency_links.txt
collective.dexteritytextindexer.egg-info/entry_points.txt
collective.dexteritytextindexer.egg-info/namespace_packages.txt
collective.dexteritytextindexer.egg-info/not-zip-safe
collective.dexteritytextindexer.egg-info/requires.txt
collective.dexteritytextindexer.egg-info/top_level.txt
collective/dexteritytextindexer/__init__.py
collective/dexteritytextindexer/behavior.py
collective/dexteritytextindexer/configure.zcml
collective/dexteritytextindexer/converters.py
collective/dexteritytextindexer/directives.py
collective/dexteritytextindexer/indexer.py
collective/dexteritytextindexer/interfaces.py
collective/dexteritytextindexer/schemaeditor.py
collective/dexteritytextindexer/supermodel.py
collective/dexteritytextindexer/testing.py
collective/dexteritytextindexer/utils.py
collective/dexteritytextindexer/tests/__init__.py
collective/dexteritytextindexer/tests/behaviors.py
collective/dexteritytextindexer/tests/behaviors.txt
collective/dexteritytextindexer/tests/configure.zcml
collective/dexteritytextindexer/tests/helpers.py
collective/dexteritytextindexer/tests/test_basic_behavior.py
collective/dexteritytextindexer/tests/test_behaviors.py
collective/dexteritytextindexer/tests/test_directives.py
collective/dexteritytextindexer/tests/test_schemaeditor.py
collective/dexteritytextindexer/tests/test_supermodel_handler.py
collective/dexteritytextindexer/tests/test_utils.py
docs/HISTORY.txt