Metadata-Version: 1.1
Name: collective.dexteritytextindexer
Version: 2.1.0
Summary: Dynamic SearchableText index for dexterity content types
Home-page: http://github.com/collective/collective.dexteritytextindexer
Author: Jonas Baumann
Author-email: mailto:info@4teamwork.ch
License: GPL2
Keywords: plone dexterity searchable text indexer
Platform: UNKNOWN
Classifier: Programming Language :: Python
Classifier: Framework :: Plone
Classifier: Framework :: Plone :: 4.2
Classifier: Framework :: Plone :: 4.3
Classifier: Topic :: Software Development :: Libraries :: Python Modules
